{"chunk_definitions":[{"chunk_id":"csetup_chunk","chunk_label":"setup","document_id":"C7F7DF0B","expansion_state":0,"options":{"engine":"r","include":false,"label":"setup"},"row":26,"row_count":1,"visible":true},{"chunk_id":"cvr20z3xmdbc4","chunk_label":"data1","document_id":"C7F7DF0B","expansion_state":0,"options":{},"row":34,"row_count":1,"visible":true},{"chunk_id":"cmkb8nbfieyh9","chunk_label":"ans11","document_id":"C7F7DF0B","expansion_state":0,"options":{},"row":44,"row_count":1,"visible":true},{"chunk_id":"crjer0pif18qa","chunk_label":"ans12","document_id":"C7F7DF0B","expansion_state":0,"options":{},"row":52,"row_count":1,"visible":true},{"chunk_id":"c7mq09vlctby8","chunk_label":"ans13","document_id":"C7F7DF0B","expansion_state":0,"options":{},"row":63,"row_count":1,"visible":true},{"chunk_id":"c6yhnicyoe70c","chunk_label":"ans14","document_id":"C7F7DF0B","expansion_state":0,"options":{},"row":73,"row_count":1,"visible":true},{"chunk_id":"ccpj802xcitx5","chunk_label":"ans15","document_id":"C7F7DF0B","expansion_state":0,"options":{},"row":87,"row_count":1,"visible":true},{"chunk_id":"caoi7znyh34db","chunk_label":"data2","document_id":"C7F7DF0B","expansion_state":0,"options":{},"row":96,"row_count":1,"visible":true},{"chunk_id":"c1wrscgf300e4","chunk_label":"ans21","document_id":"C7F7DF0B","expansion_state":0,"options":{},"row":117,"row_count":1,"visible":true},{"chunk_id":"czh83in6oweva","chunk_label":"ans22","document_id":"C7F7DF0B","expansion_state":0,"options":{},"row":126,"row_count":1,"visible":true},{"chunk_id":"cwp2gkvuw71tn","chunk_label":"ans23","document_id":"C7F7DF0B","expansion_state":0,"options":{},"row":148,"row_count":1,"visible":true},{"chunk_id":"ccw9dhddt43g0","chunk_label":"ans24","document_id":"C7F7DF0B","expansion_state":0,"options":{},"row":164,"row_count":1,"visible":true}],"default_chunk_options":{"echo":false,"eval":false},"doc_write_time":1590412022,"working_dir":null}